odoo/addons/stock_request_partner/README.rst
odoo/addons/stock_request_partner/__init__.py
odoo/addons/stock_request_partner/__manifest__.py
odoo/addons/stock_request_partner/i18n/stock_request_partner.pot
odoo/addons/stock_request_partner/models/__init__.py
odoo/addons/stock_request_partner/models/stock_request.py
odoo/addons/stock_request_partner/models/stock_request_order.py
odoo/addons/stock_request_partner/readme/CONTRIBUTORS.rst
odoo/addons/stock_request_partner/readme/DESCRIPTION.rst
odoo/addons/stock_request_partner/readme/USAGE.rst
odoo/addons/stock_request_partner/static/description/icon.png
odoo/addons/stock_request_partner/static/description/icon.svg
odoo/addons/stock_request_partner/static/description/index.html
odoo/addons/stock_request_partner/tests/__init__.py
odoo/addons/stock_request_partner/tests/test_stock_request.py
odoo/addons/stock_request_partner/views/stock_request_order_views.xml
odoo/addons/stock_request_partner/views/stock_request_views.xml
odoo14_addon_stock_request_partner-14.0.1.0.1.dist-info/METADATA
odoo14_addon_stock_request_partner-14.0.1.0.1.dist-info/WHEEL
odoo14_addon_stock_request_partner-14.0.1.0.1.dist-info/top_level.txt
odoo14_addon_stock_request_partner-14.0.1.0.1.dist-info/RECORD
